"use strict";
Object.defineProperty(exports, "__esModule", { value: true });
exports.Opcode = void 0;
var Opcode;
(function (Opcode) {
    Opcode[Opcode["NOP"] = 0] = "NOP";
    Opcode[Opcode["ACONST_NULL"] = 1] = "ACONST_NULL";
    Opcode[Opcode["ICONST_M1"] = 2] = "ICONST_M1";
    Opcode[Opcode["ICONST_0"] = 3] = "ICONST_0";
    Opcode[Opcode["ICONST_1"] = 4] = "ICONST_1";
    Opcode[Opcode["ICONST_2"] = 5] = "ICONST_2";
    Opcode[Opcode["ICONST_3"] = 6] = "ICONST_3";
    Opcode[Opcode["ICONST_4"] = 7] = "ICONST_4";
    Opcode[Opcode["ICONST_5"] = 8] = "ICONST_5";
    Opcode[Opcode["LCONST_0"] = 9] = "LCONST_0";
    Opcode[Opcode["LCONST_1"] = 10] = "LCONST_1";
    Opcode[Opcode["FCONST_0"] = 11] = "FCONST_0";
    Opcode[Opcode["FCONST_1"] = 12] = "FCONST_1";
    Opcode[Opcode["FCONST_2"] = 13] = "FCONST_2";
    Opcode[Opcode["DCONST_0"] = 14] = "DCONST_0";
    Opcode[Opcode["DCONST_1"] = 15] = "DCONST_1";
    Opcode[Opcode["BIPUSH"] = 16] = "BIPUSH";
    Opcode[Opcode["SIPUSH"] = 17] = "SIPUSH";
    Opcode[Opcode["LDC"] = 18] = "LDC";
    Opcode[Opcode["LDC_W"] = 19] = "LDC_W";
    Opcode[Opcode["LDC2_W"] = 20] = "LDC2_W";
    Opcode[Opcode["ILOAD"] = 21] = "ILOAD";
    Opcode[Opcode["LLOAD"] = 22] = "LLOAD";
    Opcode[Opcode["FLOAD"] = 23] = "FLOAD";
    Opcode[Opcode["DLOAD"] = 24] = "DLOAD";
    Opcode[Opcode["ALOAD"] = 25] = "ALOAD";
    Opcode[Opcode["ILOAD_0"] = 26] = "ILOAD_0";
    Opcode[Opcode["ILOAD_1"] = 27] = "ILOAD_1";
    Opcode[Opcode["ILOAD_2"] = 28] = "ILOAD_2";
    Opcode[Opcode["ILOAD_3"] = 29] = "ILOAD_3";
    Opcode[Opcode["LLOAD_0"] = 30] = "LLOAD_0";
    Opcode[Opcode["LLOAD_1"] = 31] = "LLOAD_1";
    Opcode[Opcode["LLOAD_2"] = 32] = "LLOAD_2";
    Opcode[Opcode["LLOAD_3"] = 33] = "LLOAD_3";
    Opcode[Opcode["FLOAD_0"] = 34] = "FLOAD_0";
    Opcode[Opcode["FLOAD_1"] = 35] = "FLOAD_1";
    Opcode[Opcode["FLOAD_2"] = 36] = "FLOAD_2";
    Opcode[Opcode["FLOAD_3"] = 37] = "FLOAD_3";
    Opcode[Opcode["DLOAD_0"] = 38] = "DLOAD_0";
    Opcode[Opcode["DLOAD_1"] = 39] = "DLOAD_1";
    Opcode[Opcode["DLOAD_2"] = 40] = "DLOAD_2";
    Opcode[Opcode["DLOAD_3"] = 41] = "DLOAD_3";
    Opcode[Opcode["ALOAD_0"] = 42] = "ALOAD_0";
    Opcode[Opcode["ALOAD_1"] = 43] = "ALOAD_1";
    Opcode[Opcode["ALOAD_2"] = 44] = "ALOAD_2";
    Opcode[Opcode["ALOAD_3"] = 45] = "ALOAD_3";
    Opcode[Opcode["IALOAD"] = 46] = "IALOAD";
    Opcode[Opcode["LALOAD"] = 47] = "LALOAD";
    Opcode[Opcode["FALOAD"] = 48] = "FALOAD";
    Opcode[Opcode["DALOAD"] = 49] = "DALOAD";
    Opcode[Opcode["AALOAD"] = 50] = "AALOAD";
    Opcode[Opcode["BALOAD"] = 51] = "BALOAD";
    Opcode[Opcode["CALOAD"] = 52] = "CALOAD";
    Opcode[Opcode["SALOAD"] = 53] = "SALOAD";
    Opcode[Opcode["ISTORE"] = 54] = "ISTORE";
    Opcode[Opcode["LSTORE"] = 55] = "LSTORE";
    Opcode[Opcode["FSTORE"] = 56] = "FSTORE";
    Opcode[Opcode["DSTORE"] = 57] = "DSTORE";
    Opcode[Opcode["ASTORE"] = 58] = "ASTORE";
    Opcode[Opcode["ISTORE_0"] = 59] = "ISTORE_0";
    Opcode[Opcode["ISTORE_1"] = 60] = "ISTORE_1";
    Opcode[Opcode["ISTORE_2"] = 61] = "ISTORE_2";
    Opcode[Opcode["ISTORE_3"] = 62] = "ISTORE_3";
    Opcode[Opcode["LSTORE_0"] = 63] = "LSTORE_0";
    Opcode[Opcode["LSTORE_1"] = 64] = "LSTORE_1";
    Opcode[Opcode["LSTORE_2"] = 65] = "LSTORE_2";
    Opcode[Opcode["LSTORE_3"] = 66] = "LSTORE_3";
    Opcode[Opcode["FSTORE_0"] = 67] = "FSTORE_0";
    Opcode[Opcode["FSTORE_1"] = 68] = "FSTORE_1";
    Opcode[Opcode["FSTORE_2"] = 69] = "FSTORE_2";
    Opcode[Opcode["FSTORE_3"] = 70] = "FSTORE_3";
    Opcode[Opcode["DSTORE_0"] = 71] = "DSTORE_0";
    Opcode[Opcode["DSTORE_1"] = 72] = "DSTORE_1";
    Opcode[Opcode["DSTORE_2"] = 73] = "DSTORE_2";
    Opcode[Opcode["DSTORE_3"] = 74] = "DSTORE_3";
    Opcode[Opcode["ASTORE_0"] = 75] = "ASTORE_0";
    Opcode[Opcode["ASTORE_1"] = 76] = "ASTORE_1";
    Opcode[Opcode["ASTORE_2"] = 77] = "ASTORE_2";
    Opcode[Opcode["ASTORE_3"] = 78] = "ASTORE_3";
    Opcode[Opcode["IASTORE"] = 79] = "IASTORE";
    Opcode[Opcode["LASTORE"] = 80] = "LASTORE";
    Opcode[Opcode["FASTORE"] = 81] = "FASTORE";
    Opcode[Opcode["DASTORE"] = 82] = "DASTORE";
    Opcode[Opcode["AASTORE"] = 83] = "AASTORE";
    Opcode[Opcode["BASTORE"] = 84] = "BASTORE";
    Opcode[Opcode["CASTORE"] = 85] = "CASTORE";
    Opcode[Opcode["SASTORE"] = 86] = "SASTORE";
    Opcode[Opcode["POP"] = 87] = "POP";
    Opcode[Opcode["POP2"] = 88] = "POP2";
    Opcode[Opcode["DUP"] = 89] = "DUP";
    Opcode[Opcode["DUP_X1"] = 90] = "DUP_X1";
    Opcode[Opcode["DUP_X2"] = 91] = "DUP_X2";
    Opcode[Opcode["DUP2"] = 92] = "DUP2";
    Opcode[Opcode["DUP2_X1"] = 93] = "DUP2_X1";
    Opcode[Opcode["DUP2_X2"] = 94] = "DUP2_X2";
    Opcode[Opcode["SWAP"] = 95] = "SWAP";
    Opcode[Opcode["IADD"] = 96] = "IADD";
    Opcode[Opcode["LADD"] = 97] = "LADD";
    Opcode[Opcode["FADD"] = 98] = "FADD";
    Opcode[Opcode["DADD"] = 99] = "DADD";
    Opcode[Opcode["ISUB"] = 100] = "ISUB";
    Opcode[Opcode["LSUB"] = 101] = "LSUB";
    Opcode[Opcode["FSUB"] = 102] = "FSUB";
    Opcode[Opcode["DSUB"] = 103] = "DSUB";
    Opcode[Opcode["IMUL"] = 104] = "IMUL";
    Opcode[Opcode["LMUL"] = 105] = "LMUL";
    Opcode[Opcode["FMUL"] = 106] = "FMUL";
    Opcode[Opcode["DMUL"] = 107] = "DMUL";
    Opcode[Opcode["IDIV"] = 108] = "IDIV";
    Opcode[Opcode["LDIV"] = 109] = "LDIV";
    Opcode[Opcode["FDIV"] = 110] = "FDIV";
    Opcode[Opcode["DDIV"] = 111] = "DDIV";
    Opcode[Opcode["IREM"] = 112] = "IREM";
    Opcode[Opcode["LREM"] = 113] = "LREM";
    Opcode[Opcode["FREM"] = 114] = "FREM";
    Opcode[Opcode["DREM"] = 115] = "DREM";
    Opcode[Opcode["INEG"] = 116] = "INEG";
    Opcode[Opcode["LNEG"] = 117] = "LNEG";
    Opcode[Opcode["FNEG"] = 118] = "FNEG";
    Opcode[Opcode["DNEG"] = 119] = "DNEG";
    Opcode[Opcode["ISHL"] = 120] = "ISHL";
    Opcode[Opcode["LSHL"] = 121] = "LSHL";
    Opcode[Opcode["ISHR"] = 122] = "ISHR";
    Opcode[Opcode["LSHR"] = 123] = "LSHR";
    Opcode[Opcode["IUSHR"] = 124] = "IUSHR";
    Opcode[Opcode["LUSHR"] = 125] = "LUSHR";
    Opcode[Opcode["IAND"] = 126] = "IAND";
    Opcode[Opcode["LAND"] = 127] = "LAND";
    Opcode[Opcode["IOR"] = 128] = "IOR";
    Opcode[Opcode["LOR"] = 129] = "LOR";
    Opcode[Opcode["IXOR"] = 130] = "IXOR";
    Opcode[Opcode["LXOR"] = 131] = "LXOR";
    Opcode[Opcode["IINC"] = 132] = "IINC";
    Opcode[Opcode["I2L"] = 133] = "I2L";
    Opcode[Opcode["I2F"] = 134] = "I2F";
    Opcode[Opcode["I2D"] = 135] = "I2D";
    Opcode[Opcode["L2I"] = 136] = "L2I";
    Opcode[Opcode["L2F"] = 137] = "L2F";
    Opcode[Opcode["L2D"] = 138] = "L2D";
    Opcode[Opcode["F2I"] = 139] = "F2I";
    Opcode[Opcode["F2L"] = 140] = "F2L";
    Opcode[Opcode["F2D"] = 141] = "F2D";
    Opcode[Opcode["D2I"] = 142] = "D2I";
    Opcode[Opcode["D2L"] = 143] = "D2L";
    Opcode[Opcode["D2F"] = 144] = "D2F";
    Opcode[Opcode["I2B"] = 145] = "I2B";
    Opcode[Opcode["I2C"] = 146] = "I2C";
    Opcode[Opcode["I2S"] = 147] = "I2S";
    Opcode[Opcode["LCMP"] = 148] = "LCMP";
    Opcode[Opcode["FCMPL"] = 149] = "FCMPL";
    Opcode[Opcode["FCMPG"] = 150] = "FCMPG";
    Opcode[Opcode["DCMPL"] = 151] = "DCMPL";
    Opcode[Opcode["DCMPG"] = 152] = "DCMPG";
    Opcode[Opcode["IFEQ"] = 153] = "IFEQ";
    Opcode[Opcode["IFNE"] = 154] = "IFNE";
    Opcode[Opcode["IFLT"] = 155] = "IFLT";
    Opcode[Opcode["IFGE"] = 156] = "IFGE";
    Opcode[Opcode["IFGT"] = 157] = "IFGT";
    Opcode[Opcode["IFLE"] = 158] = "IFLE";
    Opcode[Opcode["IF_ICMPEQ"] = 159] = "IF_ICMPEQ";
    Opcode[Opcode["IF_ICMPNE"] = 160] = "IF_ICMPNE";
    Opcode[Opcode["IF_ICMPLT"] = 161] = "IF_ICMPLT";
    Opcode[Opcode["IF_ICMPGE"] = 162] = "IF_ICMPGE";
    Opcode[Opcode["IF_ICMPGT"] = 163] = "IF_ICMPGT";
    Opcode[Opcode["IF_ICMPLE"] = 164] = "IF_ICMPLE";
    Opcode[Opcode["IF_ACMPEQ"] = 165] = "IF_ACMPEQ";
    Opcode[Opcode["IF_ACMPNE"] = 166] = "IF_ACMPNE";
    Opcode[Opcode["GOTO"] = 167] = "GOTO";
    Opcode[Opcode["JSR"] = 168] = "JSR";
    Opcode[Opcode["RET"] = 169] = "RET";
    Opcode[Opcode["TABLESWITCH"] = 170] = "TABLESWITCH";
    Opcode[Opcode["LOOKUPSWITCH"] = 171] = "LOOKUPSWITCH";
    Opcode[Opcode["IRETURN"] = 172] = "IRETURN";
    Opcode[Opcode["LRETURN"] = 173] = "LRETURN";
    Opcode[Opcode["FRETURN"] = 174] = "FRETURN";
    Opcode[Opcode["DRETURN"] = 175] = "DRETURN";
    Opcode[Opcode["ARETURN"] = 176] = "ARETURN";
    Opcode[Opcode["RETURN"] = 177] = "RETURN";
    Opcode[Opcode["GETSTATIC"] = 178] = "GETSTATIC";
    Opcode[Opcode["PUTSTATIC"] = 179] = "PUTSTATIC";
    Opcode[Opcode["GETFIELD"] = 180] = "GETFIELD";
    Opcode[Opcode["PUTFIELD"] = 181] = "PUTFIELD";
    Opcode[Opcode["INVOKEVIRTUAL"] = 182] = "INVOKEVIRTUAL";
    Opcode[Opcode["INVOKESPECIAL"] = 183] = "INVOKESPECIAL";
    Opcode[Opcode["INVOKESTATIC"] = 184] = "INVOKESTATIC";
    Opcode[Opcode["INVOKEINTERFACE"] = 185] = "INVOKEINTERFACE";
    Opcode[Opcode["NEW"] = 187] = "NEW";
    Opcode[Opcode["NEWARRAY"] = 188] = "NEWARRAY";
    Opcode[Opcode["ANEWARRAY"] = 189] = "ANEWARRAY";
    Opcode[Opcode["ARRAYLENGTH"] = 190] = "ARRAYLENGTH";
    Opcode[Opcode["ATHROW"] = 191] = "ATHROW";
    Opcode[Opcode["CHECKCAST"] = 192] = "CHECKCAST";
    Opcode[Opcode["INSTANCEOF"] = 193] = "INSTANCEOF";
    Opcode[Opcode["MONITORENTER"] = 194] = "MONITORENTER";
    Opcode[Opcode["MONITOREXIT"] = 195] = "MONITOREXIT";
    Opcode[Opcode["WIDE"] = 196] = "WIDE";
    Opcode[Opcode["MULTIANEWARRAY"] = 197] = "MULTIANEWARRAY";
    Opcode[Opcode["IFNULL"] = 198] = "IFNULL";
    Opcode[Opcode["IFNONNULL"] = 199] = "IFNONNULL";
    Opcode[Opcode["GOTO_W"] = 200] = "GOTO_W";
    Opcode[Opcode["JSR_W"] = 201] = "JSR_W";
})(Opcode = exports.Opcode || (exports.Opcode = {}));
//# sourceMappingURL=opcodes.js.map